odoo/addons/sale_stock_secondary_unit/README.rst
odoo/addons/sale_stock_secondary_unit/__init__.py
odoo/addons/sale_stock_secondary_unit/__manifest__.py
odoo/addons/sale_stock_secondary_unit/i18n/ca.po
odoo/addons/sale_stock_secondary_unit/i18n/de.po
odoo/addons/sale_stock_secondary_unit/i18n/es.po
odoo/addons/sale_stock_secondary_unit/i18n/sale_stock_secondary_unit.pot
odoo/addons/sale_stock_secondary_unit/models/__init__.py
odoo/addons/sale_stock_secondary_unit/models/procurement_rule.py
odoo/addons/sale_stock_secondary_unit/readme/CONTRIBUTORS.rst
odoo/addons/sale_stock_secondary_unit/readme/DESCRIPTION.rst
odoo/addons/sale_stock_secondary_unit/readme/USAGE.rst
odoo/addons/sale_stock_secondary_unit/static/description/icon.png
odoo/addons/sale_stock_secondary_unit/static/description/index.html
odoo/addons/sale_stock_secondary_unit/tests/__init__.py
odoo/addons/sale_stock_secondary_unit/tests/test_sale_stock_secondary_unit.py
odoo11_addon_sale_stock_secondary_unit-11.0.1.0.1.dist-info/METADATA
odoo11_addon_sale_stock_secondary_unit-11.0.1.0.1.dist-info/WHEEL
odoo11_addon_sale_stock_secondary_unit-11.0.1.0.1.dist-info/top_level.txt
odoo11_addon_sale_stock_secondary_unit-11.0.1.0.1.dist-info/RECORD
